Easebuzz/__init__.py
Easebuzz/constant.py
Easebuzz/easebuzz_payment_gateway.py
Easebuzz/payment.py
Easebuzz/payout.py
Easebuzz/refund.py
Easebuzz/refund_status.py
Easebuzz/refund_v2.py
Easebuzz/transaction.py
Easebuzz/transaction_date.py
Easebuzz/transaction_v2.py
Easebuzz/utility.py
Easebuzz-1.0.4.dist-info/METADATA
Easebuzz-1.0.4.dist-info/WHEEL
Easebuzz-1.0.4.dist-info/top_level.txt
Easebuzz-1.0.4.dist-info/RECORD
