Metadata-Version: 2.1
Name: Easebuzz
Version: 1.0.4
Summary: Wrapper to integrate functionalities of Easebuzz Payment Gateway
Home-page: 
Author: Easebuzz Payments
Author-email: root@easebuzz.in
License: MIT
Classifier: Programming Language :: Python :: 3
Classifier: License :: OSI Approved :: MIT License
Classifier: Operating System :: OS Independent
Requires-Python: >=3.10
Requires-Dist: requests
Provides-Extra: dev
Requires-Dist: twine >=4.0.2 ; extra == 'dev'
